dash_charty/DashCharty.py
dash_charty/__init__.py
dash_charty/_imports_.py
dash_charty/dash_charty.min.js
dash_charty/dash_charty.min.js.map
dash_charty/metadata.json
dash_charty/package-info.json
dash_charty-0.0.1.dist-info/LICENSE
dash_charty-0.0.1.dist-info/METADATA
dash_charty-0.0.1.dist-info/WHEEL
dash_charty-0.0.1.dist-info/top_level.txt
dash_charty-0.0.1.dist-info/RECORD
