Metadata-Version: 2.1
Name: dash-charty
Version: 0.0.1
Summary: chartly for dash
Author: pip install python <pipinstallpython@gmail.com>
License: MIT
Classifier: Framework :: Dash
License-File: LICENSE
